traylinx/__init__.py
traylinx/__main__.py
traylinx/auth.py
traylinx/branding.py
traylinx/cli.py
traylinx/constants.py
traylinx/context.py
traylinx/plugins.py
traylinx/api/__init__.py
traylinx/api/registry.py
traylinx/commands/__init__.py
traylinx/commands/assets.py
traylinx/commands/auth.py
traylinx/commands/docker_cmd.py
traylinx/commands/help.py
traylinx/commands/init.py
traylinx/commands/open_cmd.py
traylinx/commands/orgs.py
traylinx/commands/plugin.py
traylinx/commands/projects.py
traylinx/commands/publish.py
traylinx/commands/stargate.py
traylinx/commands/status.py
traylinx/commands/validate.py
traylinx/models/__init__.py
traylinx/models/manifest.py
traylinx/templates/basic/Dockerfile
traylinx/templates/basic/README.md.j2
traylinx/templates/basic/pyproject.toml.j2
traylinx/templates/basic/traylinx-agent.yaml.j2
traylinx/templates/basic/app/__init__.py.j2
traylinx/templates/basic/app/main.py.j2
traylinx/utils/__init__.py
traylinx/utils/config.py
traylinx/utils/docker.py
traylinx/utils/registry.py
traylinx_cli-0.2.1.dist-info/METADATA
traylinx_cli-0.2.1.dist-info/WHEEL
traylinx_cli-0.2.1.dist-info/entry_points.txt
traylinx_cli-0.2.1.dist-info/licenses/LICENSE
traylinx_cli-0.2.1.dist-info/RECORD
