Metadata-Version: 2.4
Name: traylinx-cli
Version: 0.2.1
Summary: CLI for the Traylinx Agent Network - Create, validate, and publish agents
Project-URL: Homepage, https://traylinx.com
Project-URL: Documentation, https://docs.traylinx.com/cli
Project-URL: Repository, https://github.com/traylinx/traylinx-cli
Author-email: Traylinx <dev@traylinx.com>
License: MIT
License-File: LICENSE
Keywords: a2a,agents,ai,cli,traylinx
Classifier: Development Status :: 3 - Alpha
Classifier: Environment :: Console
Classifier: Intended Audience :: Developers
Classifier: License :: OSI Approved :: MIT License
Classifier: Programming Language :: Python :: 3.11
Classifier: Programming Language :: Python :: 3.12
Classifier: Topic :: Software Development :: Code Generators
Requires-Python: >=3.11
Requires-Dist: email-validator>=2.0.0
Requires-Dist: httpx>=0.27.0
Requires-Dist: inquirerpy>=0.3.4
Requires-Dist: jinja2>=3.1.0
Requires-Dist: pydantic>=2.5.0
Requires-Dist: pyyaml>=6.0.0
Requires-Dist: rich>=13.0.0
Requires-Dist: typer>=0.12.0
